Metadata-Version: 2.2
Name: noty-cli
Version: 1.0.0
Summary: A terminal-based note-taking application with vim-like navigation
Home-page: https://github.com/replit/noty
Author: Replit User
Author-email: Replit User <user@replit.com>
Project-URL: Homepage, https://github.com/replit/noty
Classifier: Programming Language :: Python :: 3
Classifier: License :: OSI Approved :: MIT License
Classifier: Operating System :: OS Independent
Classifier: Environment :: Console :: Curses
Classifier: Topic :: Text Editors :: Text Processing
Requires-Python: >=3.6
Requires-Dist: windows-curses; platform_system == "Windows"
Dynamic: author
Dynamic: home-page
Dynamic: requires-python
